movenet_pre_processor/__init__.py
movenet_pre_processor/build_dataset.py
movenet_pre_processor/custom_layers.py
movenet_pre_processor/normalizer.py
movenet_pre_processor/pre_processor.py
movenet_pre_processor-1.1.0.dist-info/LICENSE
movenet_pre_processor-1.1.0.dist-info/METADATA
movenet_pre_processor-1.1.0.dist-info/WHEEL
movenet_pre_processor-1.1.0.dist-info/RECORD
