Metadata-Version: 2.1
Name: movenet-pre-processor
Version: 1.1.0
Summary: 
Author: will-s-stone
Author-email: will@williamstone.me
Requires-Python: >=3.12,<3.13
Classifier: Programming Language :: Python :: 3
Classifier: Programming Language :: Python :: 3.12
Requires-Dist: numpy (==1.26.0)
Requires-Dist: tensorflow (>=2.19.0,<3.0.0)
